hyperate/__init__.py
hyperate/hyperate.py
hyperate-1.0.1.dist-info/licenses/LICENSE
hyperate-1.0.1.dist-info/METADATA
hyperate-1.0.1.dist-info/WHEEL
hyperate-1.0.1.dist-info/top_level.txt
hyperate-1.0.1.dist-info/RECORD
