Metadata-Version: 2.4
Name: hyperate
Version: 1.0.1
Summary: Python client for the HypeRate WebSocket API
Home-page: https://hyperate.io/
Author: Serpensin
Author-email: serpensin@serpensin.com
License: MIT
Project-URL: Documentation, https://github.com/Serpensin/HypeRate-Python#readme
Project-URL: Source, https://github.com/Serpensin/HypeRate-Python
Project-URL: Homepage, https://hyperate.io/
Project-URL: Bug Reports, https://github.com/Serpensin/HypeRate-Python/issues
Classifier: Development Status :: 5 - Production/Stable
Classifier: Programming Language :: Python
Classifier: Programming Language :: Python :: 3
Classifier: Programming Language :: Python :: 3.8
Classifier: Programming Language :: Python :: 3.9
Classifier: Programming Language :: Python :: 3.10
Classifier: Programming Language :: Python :: 3.11
Classifier: Programming Language :: Python :: 3.12
Classifier: Programming Language :: Python :: 3.13
Classifier: Programming Language :: Python :: 3.14
Classifier: Operating System :: OS Independent
Classifier: Intended Audience :: Developers
Classifier: Intended Audience :: Science/Research
Classifier: Topic :: Software Development :: Libraries :: Python Modules
Classifier: Topic :: Software Development :: Libraries
Classifier: Topic :: Communications :: Conferencing
Classifier: Topic :: Utilities
Classifier: License :: OSI Approved :: MIT License
Requires-Python: >=3.8
License-File: LICENSE
Requires-Dist: websockets>=10.0
Dynamic: author
Dynamic: author-email
Dynamic: classifier
Dynamic: description
Dynamic: description-content-type
Dynamic: home-page
Dynamic: license
Dynamic: license-file
Dynamic: project-url
Dynamic: requires-dist
Dynamic: requires-python
Dynamic: summary
